[
    {
        "head": "segar Klub",
        "title": "Promo: buat mingguan Shopping Stick",
        "description": "Dapatkan Poin di setiap keranjang dan buka Anggota keuntungan yang dorong ulang Kunjungan."
    },
    {
        "head": "Sehat Picks",
        "title": "Hadiahi Pilihan yang Lebih Baik",
        "description": "Poin bonus di healthier categories. bagus Untuk kesehatan Kampanye."
    },
    {
        "head": "keluarga keranjang",
        "title": "lebih besar Cart = lebih besar Hadiah",
        "description": "dirancang Ke meningkatkan keranjang Ukuran dan frekuensi."
    },
    {
        "head": "musiman produk segar",
        "title": "musiman hemat tanpa Diskon Fatigue",
        "description": "Rotate musiman Hadiah: musim panas fruit, Kembali-Ke-school, musim dingin pantri."
    },
    {
        "head": "Anggota Prices",
        "title": "Instan Anggota penawaran",
        "description": "Anggota see Nilai immediately. ideal Untuk conversion di checkout."
    },
    {
        "head": "baru Brands",
        "title": "Discover & Dapatkan",
        "description": "dorong trial dari baru products dengan bonus-point triggers."
    }
]
